setup.py
src/ua2/__init__.py
src/ua2.mongolog.egg-info/PKG-INFO
src/ua2.mongolog.egg-info/SOURCES.txt
src/ua2.mongolog.egg-info/dependency_links.txt
src/ua2.mongolog.egg-info/eager_resources.txt
src/ua2.mongolog.egg-info/namespace_packages.txt
src/ua2.mongolog.egg-info/not-zip-safe
src/ua2.mongolog.egg-info/requires.txt
src/ua2.mongolog.egg-info/top_level.txt
src/ua2/MongoLog/__init__.py
src/ua2/MongoLog/document.py
src/ua2/MongoLog/logger.py