Metadata-Version: 1.0
Name: ua2.mongolog
Version: 0.1.1
Summary: Feed logging into MongoDB
Home-page: UNKNOWN
Author: Vic
Author-email: vic@ua2web.com
License: BSD License
Platform: UNKNOWN
